{
  "document_id": "doc-12006c216b1151c6",
  "canonical_url": "https://www.nature.com/articles/s41597-021-00817-x.pdf",
  "source_url": "https://www.nature.com/articles/s41597-021-00817-x.pdf",
  "doi": "10.1038/s41597-021-00817-x",
  "title": "https://www.nature.com/articles/s41597-021-00817-x.pdf",
  "source_domain": "www.nature.com",
  "source_tier_id": "international_institution",
  "discovery_method": "",
  "access_status": "open_full_text",
  "document_type": "pdf",
  "content_type": "application/pdf",
  "is_metadata_only": false,
  "text_hash": "12006c216b1151c6d43365a47cea063d81f4a189697df8fe48f040ae032b5936",
  "content_hash": "627f3d1fb2a905148a9f494a2dcac3d746fc657739d05d940e6b0176201eaca2",
  "text_length": 17673,
  "publication_date_hint": "",
  "source_metadata": {
    "doi": "10.1038/s41597-021-00817-x"
  },
  "artifact_path": "exploration/relationships/raw/backbone-rotation-001/fetched/001-www.nature.com.pdf",
  "parser_version": "corpus-blocks-1"
}
