{
  "document_id": "doc-00e164045e236618",
  "canonical_url": "https://doi.org/10.5716/wp18003.pdf",
  "source_url": "https://doi.org/10.5716/wp18003.pdf",
  "doi": "10.5716/wp18003.pdf",
  "title": "https://doi.org/10.5716/wp18003.pdf",
  "source_domain": "doi.org",
  "source_tier_id": "international_institution",
  "discovery_method": "",
  "access_status": "metadata_only",
  "document_type": "other",
  "content_type": "",
  "is_metadata_only": true,
  "text_hash": "",
  "content_hash": "",
  "text_length": 0,
  "publication_date_hint": "",
  "source_metadata": {
    "doi": "10.5716/wp18003.pdf"
  },
  "artifact_path": "",
  "parser_version": "corpus-blocks-1"
}
