{
  "document_id": "doc-f97ca7b90dbe0680",
  "canonical_url": "https://link.springer.com/article/10.1186/s13007-025-01473-7",
  "source_url": "https://link.springer.com/article/10.1186/s13007-025-01473-7",
  "doi": "",
  "title": "Optimized protocol for high-throughput vernalization with speed breeding in winter wheat | Plant Methods | Springer Nature Link",
  "source_domain": "link.springer.com",
  "source_tier_id": "textbook_reference",
  "discovery_method": "duckduckgo_html",
  "access_status": "open_full_text",
  "document_type": "html",
  "content_type": "text/html; charset=utf-8",
  "is_metadata_only": false,
  "text_hash": "f97ca7b90dbe0680abc5c15a56e86716880cf23b07ddca234ea3bd735bd1e486",
  "content_hash": "081b4afd9e2af4041a2f304037d3eb0ed6d663d6fa7d259294cb2d9ebca24ddb",
  "text_length": 42045,
  "publication_date_hint": "2025-12-01",
  "source_metadata": {},
  "artifact_path": "exploration/raw/pilot-global-wheat-001/fetched/478-link.springer.com.html",
  "parser_version": "corpus-blocks-1"
}
