{
  "parser_version": "corpus-blocks-1",
  "sections": [
    {
      "type": "section",
      "anchor": "sec-0",
      "level": 1,
      "heading": "Diversifying food and diets: Using agricultural biodiversity to improve nutrition and health",
      "text": ""
    },
    {
      "type": "section",
      "anchor": "sec-1",
      "level": 2,
      "heading": "Files",
      "text": "Diversifying_food_and_diets.pdf (7.36 MB)"
    },
    {
      "type": "section",
      "anchor": "sec-2",
      "level": 2,
      "heading": "Authors",
      "text": "Fanzo, Jessica Hunter, Danny Borelli, Teresa Mattei, Federico"
    },
    {
      "type": "section",
      "anchor": "sec-3",
      "level": 2,
      "heading": "Date Issued",
      "text": "2013"
    },
    {
      "type": "section",
      "anchor": "sec-4",
      "level": 2,
      "heading": "Date Online",
      "text": "2013-06-26"
    },
    {
      "type": "section",
      "anchor": "sec-5",
      "level": 2,
      "heading": "Citation",
      "text": "Fanzo, J.; Hunter, D.; Borelli, T.; Mattei, F. (eds.) (2013) Diversifying food and diets: Using agricultural biodiversity to improve nutrition and health. [Issues in Agricultural Biodiversity Series]. London (UK): Earthscan for Routledge. 400 p. ISBN: 978-1-84971-457-0"
    },
    {
      "type": "section",
      "anchor": "sec-6",
      "level": 2,
      "heading": "Abstract/Description",
      "text": "One of the world\u2019s greatest challenges is to secure adequate food that is healthy, safe and of high quality for all, and to do so in an environmentally sustainable way. This book explores the role of agricultural biodiversity as a safeguard against hunger, a source of improved dietary diversity and quality, and to strengthen local food systems and environmental sustainability."
    },
    {
      "type": "section",
      "anchor": "sec-7",
      "level": 2,
      "heading": "Permanent link to cite or share this item",
      "text": "https://hdl.handle.net/10568/76788"
    },
    {
      "type": "section",
      "anchor": "sec-8",
      "level": 2,
      "heading": "External link to download this item",
      "text": ""
    },
    {
      "type": "section",
      "anchor": "sec-9",
      "level": 2,
      "heading": "DOI",
      "text": "https://doi.org/10.4324/9780203127261"
    },
    {
      "type": "section",
      "anchor": "sec-10",
      "level": 2,
      "heading": "Author ORCID identifiers",
      "text": "Danny Hunter https://orcid.org/0000-0002-4267-595X Teresa Borelli https://orcid.org/0000-0002-6405-1339"
    },
    {
      "type": "section",
      "anchor": "sec-11",
      "level": 2,
      "heading": "Organizations Affiliated to the Authors",
      "text": "Columbia University ; Bioversity International"
    },
    {
      "type": "section",
      "anchor": "sec-12",
      "level": 2,
      "heading": "Collections",
      "text": "CTA Technical Publications Bioversity Books"
    },
    {
      "type": "section",
      "anchor": "sec-13",
      "level": 2,
      "heading": "Share",
      "text": ""
    },
    {
      "type": "section",
      "anchor": "sec-14",
      "level": 2,
      "heading": "Type",
      "text": "Book"
    },
    {
      "type": "section",
      "anchor": "sec-15",
      "level": 2,
      "heading": "Review Status",
      "text": ""
    },
    {
      "type": "section",
      "anchor": "sec-16",
      "level": 2,
      "heading": "Language",
      "text": "en"
    },
    {
      "type": "section",
      "anchor": "sec-17",
      "level": 2,
      "heading": "Subjects",
      "text": "BIODIVERSITY ; NUTRITION ; FOOD SECURITY"
    },
    {
      "type": "section",
      "anchor": "sec-18",
      "level": 2,
      "heading": "Access Rights",
      "text": "Open Access"
    },
    {
      "type": "section",
      "anchor": "sec-19",
      "level": 2,
      "heading": "Usage Rights",
      "text": "Copyrighted; all rights reserved"
    },
    {
      "type": "section",
      "anchor": "sec-20",
      "level": 2,
      "heading": "Attention",
      "text": ""
    }
  ],
  "tables": [],
  "paragraphs": [
    {
      "type": "paragraph",
      "text": "Mutwedu, V.B., Manyawu, G.J., Lukuyu, M.N. and Bacigale, S. 2020. Fodder production manual for extension staff and farmers in South Kivu and Tanganyika Provinces of the Democratic Republic of the Congo. ILRI Manual 37. Nairobi, Kenya: ILRI.",
      "char_offset": 0
    }
  ],
  "labels": [],
  "document_id": "doc-d3a0439cd03cbb9b"
}
